MANIFEST.in
README.rst
setup.py
python_teamwork.egg-info/PKG-INFO
python_teamwork.egg-info/SOURCES.txt
python_teamwork.egg-info/dependency_links.txt
python_teamwork.egg-info/not-zip-safe
python_teamwork.egg-info/requires.txt
python_teamwork.egg-info/top_level.txt
teamwork/__init__.py
teamwork/teamwork.py