Metadata-Version: 1.0
Name: python-teamwork
Version: 0.1.3
Summary: Python Wrapper for Teamwork API
Home-page: https://github.com/swappsco/python-teamwork
Author: Andres Gonzalez
Author-email: andresgz@gmail.com
License: MIT
Platform: UNKNOWN
